<?xml version="1.0" encoding="UTF-8"?>
<!DOCTYPE futbol [
    <!ELEMENT futbol (partido+)>
    <!ELEMENT partido (equipo+)>
    <!ELEMENT equipo EMPTY>
    <!ATTLIST equipo tipo (local|visitante) #REQUIRED>
    <!ATTLIST equipo nombre NMTOKENS #REQUIRED>
    <!ATTLIST equipo goles CDATA #REQUIRED>
]>

<futbol>
    <partido>
        <equipo tipo="local" nombre="Nottingham Presa" goles="0"/>
        <equipo tipo="visitante" nombre="Inter de Mitente" goles="1"/>
    </partido>
    <partido>
        <equipo tipo="local" nombre="Vodka Juniors" goles="3"/>
        <equipo tipo="visitante" nombre="Sparta da Risa" goles="3"/>
    </partido>
    <partido>
        <equipo tipo="local" nombre="Water de Munich" goles="4"/>
        <equipo tipo="visitante" nombre="Esteaua es del grifo" goles="2"/>
    </partido>
</futbol>